buoy_tracking/__init__.py
buoy_tracking/data_fetch.py
buoy_tracking/forecast_position.py
buoy_tracking/geo_tools.py
buoy_tracking/model_fetch.py
buoy_tracking/utils.py
buoy_tracking/static/active_buoys.json
buoy_tracking/static/buoy_staticvars.json
buoy_tracking-1.0.4.dist-info/METADATA
buoy_tracking-1.0.4.dist-info/WHEEL
buoy_tracking-1.0.4.dist-info/top_level.txt
buoy_tracking-1.0.4.dist-info/RECORD
