Metadata-Version: 2.1
Name: buoy-tracking
Version: 1.0.4
Home-page: https://github.com/wrightni/buoy_tracking
Author: Nicholas Wright
Requires-Dist: numpy
Requires-Dist: pandas
Requires-Dist: requests
Requires-Dist: scikit-learn
Requires-Dist: pyproj
Requires-Dist: scipy
Requires-Dist: netCDF4
Requires-Dist: lxml
